ctxpack/__init__.py
ctxpack/__main__.py
ctxpack/cli.py
ctxpack/config.py
ctxpack/graph.py
ctxpack/ignore.py
ctxpack/output.py
ctxpack/ranker.py
ctxpack/scanner.py
ctxpack/utils.py
ctxpack/watcher.py
ctxpack-0.1.0.dist-info/METADATA
ctxpack-0.1.0.dist-info/WHEEL
ctxpack-0.1.0.dist-info/entry_points.txt
ctxpack-0.1.0.dist-info/top_level.txt
ctxpack-0.1.0.dist-info/RECORD
