Metadata-Version: 2.4
Name: ctxpack
Version: 0.1.0
Summary: Automatically gather project context and generate Markdown prompt packages for LLMs
Author-email: Gabriel <gabriel@example.com>
License: MIT
Project-URL: Homepage, https://github.com/gabriel/ctxpack
Project-URL: Repository, https://github.com/gabriel/ctxpack
Keywords: llm,context,cli,markdown,developer-tools
Classifier: Development Status :: 3 - Alpha
Classifier: Environment :: Console
Classifier: Intended Audience :: Developers
Classifier: License :: OSI Approved :: MIT License
Classifier: Operating System :: OS Independent
Classifier: Programming Language :: Python :: 3
Classifier: Programming Language :: Python :: 3.11
Classifier: Programming Language :: Python :: 3.12
Classifier: Topic :: Software Development :: Documentation
Classifier: Topic :: Text Processing :: Markup :: Markdown
Requires-Python: >=3.11
Requires-Dist: typer>=0.9.0
Requires-Dist: watchdog>=3.0.0
Requires-Dist: rich>=13.0.0
Provides-Extra: dev
Requires-Dist: pytest>=7.0.0; extra == "dev"
Requires-Dist: pytest-cov>=4.0.0; extra == "dev"
